.DS_Store
tasccoda/__init__.py
tasccoda/tree_agg_model_sslasso.py
tasccoda/tree_ana.py
tasccoda/tree_results.py
tasccoda/tree_utils.py
tasccoda/datasets/__init__.py
tasccoda/datasets/_datasets.py
tascCODA-0.1.3.dist-info/LICENSE
tascCODA-0.1.3.dist-info/METADATA
tascCODA-0.1.3.dist-info/WHEEL
tascCODA-0.1.3.dist-info/top_level.txt
tascCODA-0.1.3.dist-info/RECORD
