Metadata-Version: 2.1
Name: tascCODA
Version: 0.1.3
Summary: Tree-aggregated compositional analysis for high-throughput sequencing data
Home-page: https://github.com/bio-datascience/tascCODA
Author: Johannes Ostner, Christian L. Müller
Author-email: johannes.ostner@helmholtz-muenchen.de
License: BSD
Keywords: microbiome,single cell,composition,CODA,compositional analysis,tree aggregation,tensorflow,MCMC
Classifier: License :: OSI Approved :: BSD License
Classifier: Intended Audience :: Science/Research
Classifier: Programming Language :: Python
Classifier: Programming Language :: Python :: 3
Classifier: Programming Language :: Python :: 3.8
Classifier: Topic :: Scientific/Engineering :: Bio-Informatics
Requires-Python: >=3.8.0
License-File: LICENSE
Requires-Dist: numpy
Requires-Dist: pandas
Requires-Dist: tensorflow (>=2.8)
Requires-Dist: tensorflow-probability (>=0.16)
Requires-Dist: arviz (>=0.10)
Requires-Dist: anndata
Requires-Dist: patsy
Requires-Dist: toytree
Requires-Dist: sccoda (>=0.1.7)
